MMCQsc/__init__.py
MMCQsc/__main__.py
MMCQsc/color_theme_analyse.py
MMCQsc/validation.py
MMCQsc/version.py
MMCQsc/scp/__init__.py
MMCQsc/scp/executable_check.py
MMCQsc/scp/main.py
MMCQsc/scp/lib/MMCQ.py
MMCQsc/scp/lib/__init__.py
MMCQsc/scp/lib/dpkg.py
MMCQsc/scp/lib/error_sc.py
MMCQsc/scp/lib/logger.py
MMCQsc/scp/scripts/__init__.py
MMCQsc/scp/scripts/executer.py
MMCQsc/scp/scripts/pipw.py
MMCQsc/scp/scripts/profile.json
MMCQsc/scp/scripts/psAdminOpen.reg
MMCQsc/scp/scripts/reinstallBase.vbs
MMCQsc/scp/scripts/reinstallDev.vbs
MMCQsc/scp/scripts/upgrade.vbs
color_theme_analyse-1.145.6.data/data/lib/site-packages/MMCQsc/scp/dll/CommonOpenDialogDll.dll
color_theme_analyse-1.145.6.data/data/lib/site-packages/MMCQsc/scp/dll/CommonOpenDialogDll64.dll
color_theme_analyse-1.145.6.data/data/lib/site-packages/MMCQsc/src/gitee.svg
color_theme_analyse-1.145.6.data/data/lib/site-packages/MMCQsc/src/index.html
color_theme_analyse-1.145.6.data/data/lib/site-packages/MMCQsc/src/_css/animate.css
color_theme_analyse-1.145.6.data/data/lib/site-packages/MMCQsc/src/_css/base.css
color_theme_analyse-1.145.6.data/data/lib/site-packages/MMCQsc/src/_css/sweet-alert.css
color_theme_analyse-1.145.6.data/data/lib/site-packages/MMCQsc/src/_js/babel.min_5.8.23.js
color_theme_analyse-1.145.6.data/data/lib/site-packages/MMCQsc/src/_js/base.js
color_theme_analyse-1.145.6.data/data/lib/site-packages/MMCQsc/src/_js/react-dom.development.js
color_theme_analyse-1.145.6.data/data/lib/site-packages/MMCQsc/src/_js/react.development.js
color_theme_analyse-1.145.6.data/data/lib/site-packages/MMCQsc/src/_js/sweet-alert.js
color_theme_analyse-1.145.6.data/data/lib/site-packages/MMCQsc/src/_js/wow.min.js
color_theme_analyse-1.145.6.data/data/lib/site-packages/MMCQsc/src/_js/wow.min2.js
color_theme_analyse-1.145.6.data/data/lib/site-packages/MMCQsc/src/browser/绛亽浏览器.exe
color_theme_analyse-1.145.6.data/scripts/MMCQsc.cmd
color_theme_analyse-1.145.6.dist-info/LICENSE
color_theme_analyse-1.145.6.dist-info/METADATA
color_theme_analyse-1.145.6.dist-info/WHEEL
color_theme_analyse-1.145.6.dist-info/dependency_links.txt
color_theme_analyse-1.145.6.dist-info/entry_points.txt
color_theme_analyse-1.145.6.dist-info/namespace_packages.txt
color_theme_analyse-1.145.6.dist-info/top_level.txt
color_theme_analyse-1.145.6.dist-info/RECORD
